{
  "instance_id": "ClockSetAlarm#0",
  "task": "ClockSetAlarm",
  "params": {
    "hour": 7,
    "minute": 30
  },
  "returncode": 0,
  "self_eval": {
    "success": true,
    "confidence": 0.99,
    "evidence_summary": "Alarm list screenshot shows a 07:30 alarm with toggle ON (blue), labeled '只响一次', and header confirming '5小时50分钟后响铃'.",
    "screenshot_paths": [
      "final alarm list screenshot from get_screenshot"
    ],
    "failure_reason": ""
  },
  "timing": {
    "wall_ms": 245680,
    "api_ms": 193736
  },
  "num_turns": 38,
  "cost_usd": 1.20926425,
  "stop_reason": "success",
  "num_steps": 37,
  "steps": [
    {
      "step": 1,
      "tool": "press_home",
      "input": {},
      "success": true,
      "is_error": false
    },
    {
      "step": 2,
      "tool": "wait_stable_screen",
      "input": {
        "stable_duration": 1,
        "timeout": 5
      },
      "success": true,
      "is_error": false
    },
    {
      "step": 3,
      "tool": "get_screenshot",
      "input": {
        "quality": 30
      },
      "success": true,
      "is_error": false
    },
    {
      "step": 4,
      "tool": "ai_click",
      "input": {
        "text": "时钟"
      },
      "success": true,
      "is_error": false
    },
    {
      "step": 5,
      "tool": "wait_stable_screen",
      "input": {
        "stable_duration": 1.5,
        "timeout": 5
      },
      "success": true,
      "is_error": false
    },
    {
      "step": 6,
      "tool": "get_screenshot",
      "input": {
        "quality": 30
      },
      "success": true,
      "is_error": false
    },
    {
      "step": 7,
      "tool": "ai_click",
      "input": {
        "text": "闹钟"
      },
      "success": true,
      "is_error": false
    },
    {
      "step": 8,
      "tool": "wait_stable_screen",
      "input": {
        "stable_duration": 1,
        "timeout": 5
      },
      "success": true,
      "is_error": false
    },
    {
      "step": 9,
      "tool": "get_screenshot",
      "input": {
        "quality": 30
      },
      "success": true,
      "is_error": false
    },
    {
      "step": 10,
      "tool": "ai_click",
      "input": {
        "icon": "plus button"
      },
      "success": true,
      "is_error": false
    },
    {
      "step": 11,
      "tool": "wait_stable_screen",
      "input": {
        "stable_duration": 1,
        "timeout": 5
      },
      "success": true,
      "is_error": false
    },
    {
      "step": 12,
      "tool": "get_screenshot",
      "input": {
        "quality": 30
      },
      "success": true,
      "is_error": false
    },
    {
      "step": 13,
      "tool": "get_screen_xml",
      "input": {},
      "success": true,
      "is_error": false
    },
    {
      "step": 14,
      "tool": "swipe",
      "input": {
        "from_x": 0.31,
        "from_y": 0.42,
        "to_x": 0.31,
        "to_y": 0.28,
        "duration": 500
      },
      "success": true,
      "is_error": false
    },
    {
      "step": 15,
      "tool": "wait_stable_screen",
      "input": {
        "stable_duration": 1,
        "timeout": 5
      },
      "success": true,
      "is_error": false
    },
    {
      "step": 16,
      "tool": "get_screenshot",
      "input": {
        "quality": 30
      },
      "success": true,
      "is_error": false
    },
    {
      "step": 17,
      "tool": "swipe",
      "input": {
        "from_x": 0.31,
        "from_y": 0.42,
        "to_x": 0.31,
        "to_y": 0.24,
        "duration": 500
      },
      "success": true,
      "is_error": false
    },
    {
      "step": 18,
      "tool": "wait_stable_screen",
      "input": {
        "stable_duration": 1,
        "timeout": 5
      },
      "success": true,
      "is_error": false
    },
    {
      "step": 19,
      "tool": "get_screenshot",
      "input": {
        "quality": 30
      },
      "success": true,
      "is_error": false
    },
    {
      "step": 20,
      "tool": "swipe",
      "input": {
        "from_x": 0.31,
        "from_y": 0.42,
        "to_x": 0.31,
        "to_y": 0.36,
        "duration": 300
      },
      "success": true,
      "is_error": false
    },
    {
      "step": 21,
      "tool": "wait_stable_screen",
      "input": {
        "stable_duration": 1,
        "timeout": 5
      },
      "success": true,
      "is_error": false
    },
    {
      "step": 22,
      "tool": "get_screenshot",
      "input": {
        "quality": 30
      },
      "success": true,
      "is_error": false
    },
    {
      "step": 23,
      "tool": "swipe",
      "input": {
        "from_x": 0.69,
        "from_y": 0.36,
        "to_x": 0.69,
        "to_y": 0.52,
        "duration": 500
      },
      "success": true,
      "is_error": false
    },
    {
      "step": 24,
      "tool": "wait_stable_screen",
      "input": {
        "stable_duration": 1,
        "timeout": 5
      },
      "success": true,
      "is_error": false
    },
    {
      "step": 25,
      "tool": "get_screenshot",
      "input": {
        "quality": 30
      },
      "success": true,
      "is_error": false
    },
    {
      "step": 26,
      "tool": "swipe",
      "input": {
        "from_x": 0.69,
        "from_y": 0.36,
        "to_x": 0.69,
        "to_y": 0.48,
        "duration": 400
      },
      "success": true,
      "is_error": false
    },
    {
      "step": 27,
      "tool": "wait_stable_screen",
      "input": {
        "stable_duration": 1,
        "timeout": 5
      },
      "success": true,
      "is_error": false
    },
    {
      "step": 28,
      "tool": "get_screenshot",
      "input": {
        "quality": 30
      },
      "success": true,
      "is_error": false
    },
    {
      "step": 29,
      "tool": "swipe",
      "input": {
        "from_x": 0.69,
        "from_y": 0.36,
        "to_x": 0.69,
        "to_y": 0.42,
        "duration": 300
      },
      "success": true,
      "is_error": false
    },
    {
      "step": 30,
      "tool": "wait_stable_screen",
      "input": {
        "stable_duration": 1,
        "timeout": 5
      },
      "success": true,
      "is_error": false
    },
    {
      "step": 31,
      "tool": "get_screenshot",
      "input": {
        "quality": 30
      },
      "success": true,
      "is_error": false
    },
    {
      "step": 32,
      "tool": "swipe",
      "input": {
        "from_x": 0.69,
        "from_y": 0.38,
        "to_x": 0.69,
        "to_y": 0.42,
        "duration": 200
      },
      "success": true,
      "is_error": false
    },
    {
      "step": 33,
      "tool": "wait_stable_screen",
      "input": {
        "stable_duration": 1,
        "timeout": 5
      },
      "success": true,
      "is_error": false
    },
    {
      "step": 34,
      "tool": "get_screenshot",
      "input": {
        "quality": 30
      },
      "success": true,
      "is_error": false
    },
    {
      "step": 35,
      "tool": "ai_click",
      "input": {
        "icon": "checkmark button top right"
      },
      "success": true,
      "is_error": false
    },
    {
      "step": 36,
      "tool": "wait_stable_screen",
      "input": {
        "stable_duration": 1.5,
        "timeout": 5
      },
      "success": true,
      "is_error": false
    },
    {
      "step": 37,
      "tool": "get_screenshot",
      "input": {
        "quality": 30
      },
      "success": true,
      "is_error": false
    }
  ]
}