{
  "instance_id": "SettingsCheckAboutPhone#0",
  "task": "SettingsCheckAboutPhone",
  "params": {},
  "returncode": 0,
  "self_eval": {
    "success": true,
    "confidence": 0.98,
    "evidence_summary": "全部参数与信息页面同时显示设备型号 REDMI Note 15 和 Android 版本 15（安全更新 2025-07-01）",
    "screenshot_paths": [
      "wimb-device get_screenshot - 我的设备 > 全部参数与信息页"
    ],
    "failure_reason": ""
  },
  "timing": {
    "wall_ms": 104712,
    "api_ms": 75680
  },
  "num_turns": 14,
  "cost_usd": 0.5057765,
  "stop_reason": "success",
  "num_steps": 13,
  "steps": [
    {
      "step": 1,
      "tool": "ToolSearch",
      "input": {
        "query": "select:mcp__wimb-device__press_home,mcp__wimb-device__get_screenshot,mcp__wimb-device__open_app,mcp__wimb-device__ai_click,mcp__wimb-device__swipe,mcp__wimb-device__wait_stable_screen,mcp__wimb-device__get_screen_xml,mcp__wimb-device__press_back",
        "max_results": 10
      },
      "success": true,
      "is_error": false
    },
    {
      "step": 2,
      "tool": "press_home",
      "input": {},
      "success": true,
      "is_error": false
    },
    {
      "step": 3,
      "tool": "open_app",
      "input": {
        "package_name": "com.android.settings"
      },
      "success": true,
      "is_error": false
    },
    {
      "step": 4,
      "tool": "wait_stable_screen",
      "input": {},
      "success": true,
      "is_error": false
    },
    {
      "step": 5,
      "tool": "get_screenshot",
      "input": {
        "quality": 15
      },
      "success": true,
      "is_error": false
    },
    {
      "step": 6,
      "tool": "ai_click",
      "input": {
        "text": "我的设备"
      },
      "success": true,
      "is_error": false
    },
    {
      "step": 7,
      "tool": "wait_stable_screen",
      "input": {},
      "success": true,
      "is_error": false
    },
    {
      "step": 8,
      "tool": "get_screenshot",
      "input": {
        "quality": 15
      },
      "success": true,
      "is_error": false
    },
    {
      "step": 9,
      "tool": "swipe",
      "input": {
        "from_x": 0.5,
        "from_y": 0.8,
        "to_x": 0.5,
        "to_y": 0.2
      },
      "success": true,
      "is_error": false
    },
    {
      "step": 10,
      "tool": "get_screenshot",
      "input": {
        "quality": 15
      },
      "success": true,
      "is_error": false
    },
    {
      "step": 11,
      "tool": "ai_click",
      "input": {
        "text": "全部参数与信息"
      },
      "success": true,
      "is_error": false
    },
    {
      "step": 12,
      "tool": "wait_stable_screen",
      "input": {},
      "success": true,
      "is_error": false
    },
    {
      "step": 13,
      "tool": "get_screenshot",
      "input": {
        "quality": 15
      },
      "success": true,
      "is_error": false
    }
  ]
}